README.md
setup.py
japantime.egg-info/PKG-INFO
japantime.egg-info/SOURCES.txt
japantime.egg-info/dependency_links.txt
japantime.egg-info/top_level.txt
jtime/__init__.py