Metadata-Version: 2.1
Name: japantime
Version: 1.1.9
Author: inu
License: MIT
